keithley2600/__init__.py
keithley2600/keithley_driver.py
keithley2600/result_table.py
keithley2600-2.0.2.dist-info/LICENSE.txt
keithley2600-2.0.2.dist-info/METADATA
keithley2600-2.0.2.dist-info/WHEEL
keithley2600-2.0.2.dist-info/top_level.txt
keithley2600-2.0.2.dist-info/RECORD
