Metadata-Version: 2.1
Name: keithley2600
Version: 2.0.2
Summary: Full Python driver for the Keithley 2600 series.
Home-page: https://github.com/OE-FET/keithley2600.git
Author: Sam Schott
Author-email: ss2151@cam.ac.uk
License: MIT
Platform: UNKNOWN
Classifier: License :: OSI Approved :: MIT License
Classifier: Programming Language :: Python
Classifier: Programming Language :: Python :: 3.6
Classifier: Programming Language :: Python :: 3.7
Classifier: Programming Language :: Python :: 3.8
Classifier: Programming Language :: Python :: 3.9
License-File: LICENSE.txt
Requires-Dist: pyvisa
Requires-Dist: pyvisa-py
Requires-Dist: numpy
